pysysq/__init__.py
pysysq/__main__.py
pysysq/_version.py
pysysq/logging.conf
pysysq/sq_base/__init__.py
pysysq/sq_base/sq_object.py
pysysq/sq_base/sq_time_base.py
pysysq/sq_base/sq_clock/__init__.py
pysysq/sq_base/sq_clock/sq_clock.py
pysysq/sq_base/sq_event/__init__.py
pysysq/sq_base/sq_event/sq_event.py
pysysq/sq_base/sq_event/sq_event_manager.py
pysysq/sq_base/sq_event/sq_event_queue.py
pysysq/sq_base/sq_factory/__init__.py
pysysq/sq_base/sq_factory/sq_factory.py
pysysq/sq_base/sq_factory/sq_helper_factory.py
pysysq/sq_base/sq_filter/__init__.py
pysysq/sq_base/sq_filter/sq_filter.py
pysysq/sq_base/sq_logger/__init__.py
pysysq/sq_base/sq_logger/sq_logger.py
pysysq/sq_base/sq_merger/__init__.py
pysysq/sq_base/sq_merger/sq_merger.py
pysysq/sq_base/sq_mux_demux/__init__.py
pysysq/sq_base/sq_mux_demux/sq_demux.py
pysysq/sq_base/sq_mux_demux/sq_mux.py
pysysq/sq_base/sq_packet/__init__.py
pysysq/sq_base/sq_packet/sq_metadata.py
pysysq/sq_base/sq_packet/sq_packet.py
pysysq/sq_base/sq_pkt_gen/__init__.py
pysysq/sq_base/sq_pkt_gen/sq_pkt_gen.py
pysysq/sq_base/sq_pkt_gen/states/__init__.py
pysysq/sq_base/sq_pkt_gen/states/sq_generator_state.py
pysysq/sq_base/sq_pkt_gen/states/sq_generator_state_factory.py
pysysq/sq_base/sq_pkt_gen/states/sq_pkt_generator_gen_state.py
pysysq/sq_base/sq_pkt_gen/states/sq_pkt_generator_queuing_state.py
pysysq/sq_base/sq_pkt_processor/__init__.py
pysysq/sq_base/sq_pkt_processor/sq_pkt_processor.py
pysysq/sq_base/sq_pkt_processor/states/__init__.py
pysysq/sq_base/sq_pkt_processor/states/sq_pkt_proc_complete.py
pysysq/sq_base/sq_pkt_processor/states/sq_pkt_proc_idle.py
pysysq/sq_base/sq_pkt_processor/states/sq_pkt_proc_processing.py
pysysq/sq_base/sq_pkt_processor/states/sq_pkt_processor_state.py
pysysq/sq_base/sq_pkt_processor/states/sq_state_factory.py
pysysq/sq_base/sq_pkt_sink/__init__.py
pysysq/sq_base/sq_pkt_sink/sq_pkt_sink.py
pysysq/sq_base/sq_plugin/__init__.py
pysysq/sq_base/sq_plugin/sq_helper.py
pysysq/sq_base/sq_plugin/sq_plugin.py
pysysq-0.2.0.dist-info/LICENSE
pysysq-0.2.0.dist-info/METADATA
pysysq-0.2.0.dist-info/WHEEL
pysysq-0.2.0.dist-info/top_level.txt
pysysq-0.2.0.dist-info/RECORD
