Metadata-Version: 2.1
Name: pysysq
Version: 0.2.0
Summary: A system functional flow simulation framework using Queuing Theory
Author-email: Ajith Padman <ajith.padman@gmail.com>
License: MIT License
Project-URL: Homepage, https://github.com/ajithpadman/PysysQ
Project-URL: Issues, https://github.com/ajithpadman/PysysQ/issues
Classifier: Development Status :: 3 - Alpha
Classifier: Programming Language :: Python :: 3
Classifier: License :: OSI Approved :: MIT License
Classifier: Operating System :: OS Independent
Classifier: Programming Language :: Python :: 3.10
Requires-Python: >=3.10
License-File: LICENSE
Requires-Dist: contourpy >=1.2.0
Requires-Dist: cycler >=0.12.1
Requires-Dist: fonttools >=4.49.0
Requires-Dist: Jinja2 >=3.1.3
Requires-Dist: kiwisolver >=1.4.5
Requires-Dist: markdown-it-py >=3.0.0
Requires-Dist: MarkupSafe >=2.1.5
Requires-Dist: matplotlib >=3.8.3
Requires-Dist: mdurl >=0.1.2
Requires-Dist: numpy >=1.26.4
Requires-Dist: packaging >=23.2
Requires-Dist: pandas >=2.2.1
Requires-Dist: pillow >=10.2.0
Requires-Dist: Pygments >=2.17.2
Requires-Dist: pyparsing >=3.1.1
Requires-Dist: PySide2 >=5.15.2.1
Requires-Dist: python-dateutil >=2.9.0.post0
Requires-Dist: pytz >=2024.1
Requires-Dist: rich >=13.7.1
Requires-Dist: shiboken2 >=5.15.2.1
Requires-Dist: six >=1.16.0
Requires-Dist: tzdata >=2024.1
Requires-Dist: XlsxWriter >=3.2.0
